pytwgasprices/__init__.py
pytwgasprices/cpcgas.py
pytwgasprices/fpccgas.py
pytwgasprices-0.0.1.dist-info/LICENSE
pytwgasprices-0.0.1.dist-info/METADATA
pytwgasprices-0.0.1.dist-info/WHEEL
pytwgasprices-0.0.1.dist-info/top_level.txt
pytwgasprices-0.0.1.dist-info/RECORD
